cbot.py
cbot_command-1.0.3.dist-info/LICENSE
cbot_command-1.0.3.dist-info/METADATA
cbot_command-1.0.3.dist-info/WHEEL
cbot_command-1.0.3.dist-info/entry_points.txt
cbot_command-1.0.3.dist-info/top_level.txt
cbot_command-1.0.3.dist-info/RECORD
