Metadata-Version: 2.1
Name: cbot-command
Version: 1.0.3
Summary: Cbot is a simple python command line bot based on GPT3.
Home-page: https://github.com/graiz/cbot/
Author: Gregory Raiz
Author-email: 
Project-URL: GitHub, https://github.com/graiz/cbot/
Keywords: terminal cbot openai gpt3 chatgpt
Classifier: Programming Language :: Python :: 3
Classifier: License :: OSI Approved :: MIT License
Requires-Python: >=3.6
License-File: LICENSE
Requires-Dist: openai
Requires-Dist: pyperclip
